[
    {
        "id": 2,
        "name": "Meg",
        "url": "https:\/\/i.imgur.com\/UU7wyLJ.png",
        "description": "XD",
        "tags": [
            "XD"
        ],
        "type": "normal"
    },
    {
        "id": 2,
        "name": "Cami",
        "description": "Cami de fnafhs",
        "tags": [
            "fnafhs",
            "ballgag",
            "schoolgirl",
            "cringe"
        ],
        "url": "https:\/\/i.imgur.com\/QivDP4q.jpeg",
        "type": "normal"
    }
]